CHANGES.rst
LICENSE
MANIFEST.in
README.rst
package.json
setup.py
armstrong/__init__.py
armstrong.apps.embeds.egg-info/PKG-INFO
armstrong.apps.embeds.egg-info/SOURCES.txt
armstrong.apps.embeds.egg-info/dependency_links.txt
armstrong.apps.embeds.egg-info/namespace_packages.txt
armstrong.apps.embeds.egg-info/requires.txt
armstrong.apps.embeds.egg-info/top_level.txt
armstrong/apps/__init__.py
armstrong/apps/embeds/__init__.py
armstrong/apps/embeds/admin.py
armstrong/apps/embeds/admin_forms.py
armstrong/apps/embeds/fields.py
armstrong/apps/embeds/forms.py
armstrong/apps/embeds/mixins.py
armstrong/apps/embeds/models.py
armstrong/apps/embeds/backends/__init__.py
armstrong/apps/embeds/backends/base_response.py
armstrong/apps/embeds/backends/default.py
armstrong/apps/embeds/backends/embedly.py
armstrong/apps/embeds/backends/twitter.py
armstrong/apps/embeds/backends/twitterembedly.py
armstrong/apps/embeds/backends/youtube.py
armstrong/apps/embeds/fixtures/embed_backends.json
armstrong/apps/embeds/migrations/0001_initial.py
armstrong/apps/embeds/migrations/__init__.py
armstrong/apps/embeds/south_migrations/0001_initial.py
armstrong/apps/embeds/south_migrations/__init__.py
armstrong/apps/embeds/templates/embeds/admin/change_list_template.html
armstrong/apps/embeds/templates/embeds/admin/embed_change_form.html
armstrong/apps/embeds/templates/layout/embeds/embed/default.html
armstrong/apps/embeds/templates/layout/embeds/embed/full.html
armstrong/apps/embeds/templates/layout/embeds/embed/thumb.html
armstrong/apps/embeds/templates/layout/embeds/embedtype/link/.include_in_git
armstrong/apps/embeds/templates/layout/embeds/embedtype/photo/full.html
armstrong/apps/embeds/templates/layout/embeds/embedtype/photo/thumb.html
armstrong/apps/embeds/templates/layout/embeds/embedtype/rich/thumb.html
armstrong/apps/embeds/templates/layout/embeds/embedtype/video/full.html
armstrong/apps/embeds/templates/layout/embeds/embedtype/video/thumb.html
armstrong/apps/embeds/templatetags/__init__.py
armstrong/apps/embeds/templatetags/embed_helpers.py