Metadata-Version: 1.1
Name: armstrong.apps.embeds
Version: 0.9
Summary: Provides a way to store, relate to, extract metadata and embed content from external URLs via a modular backend system
Home-page: http://github.com/armstrong/armstrong.apps.embeds/
Author: Texas Tribune & The Center for Investigative Reporting
Author-email: dev@armstrongcms.org
License: UNKNOWN
Platform: UNKNOWN
Classifier: Development Status :: 4 - Beta
Classifier: Environment :: Web Environment
Classifier: Framework :: Django
Classifier: Intended Audience :: Developers
Classifier: License :: OSI Approved :: Apache Software License
Classifier: Operating System :: OS Independent
Classifier: Programming Language :: Python
Classifier: Programming Language :: Python :: 2.6
Classifier: Programming Language :: Python :: 2.7
